CONTRIBUTING.rst
LICENSE
MANIFEST.in
README.rst
pyproject.toml
setup.cfg
setup.py
docs/Makefile
docs/source/authors.rst
docs/source/conf.py
docs/source/contributing.rst
docs/source/index.rst
docs/source/installation.rst
docs/source/usage.rst
docs/source/diagrams/git_flow.png
repomanager/__init__.py
repomanager/constants.py
repomanager/log.py
repomanager/main.py
repomanager/rpm.py
repomanager/utils.py
repomanager.egg-info/PKG-INFO
repomanager.egg-info/SOURCES.txt
repomanager.egg-info/dependency_links.txt
repomanager.egg-info/entry_points.txt
repomanager.egg-info/not-zip-safe
repomanager.egg-info/top_level.txt
tests/__init__.py
tests/test_repomanager.py